crispr_ambiguous_mapping/__init__.py
crispr_ambiguous_mapping/mapping/__init__.py
crispr_ambiguous_mapping/mapping/main_mapping.py
crispr_ambiguous_mapping/models/__init__.py
crispr_ambiguous_mapping/models/editing_models.py
crispr_ambiguous_mapping/models/error_models.py
crispr_ambiguous_mapping/models/mapping_models.py
crispr_ambiguous_mapping/models/quality_control_models.py
crispr_ambiguous_mapping/parsing/__init__.py
crispr_ambiguous_mapping/parsing/guide_raw_fastq_parsing.py
crispr_ambiguous_mapping/parsing/reporter_standard_fastq_parsing.py
crispr_ambiguous_mapping/parsing/reporter_tsv_parsing.py
crispr_ambiguous_mapping/parsing/reporter_umitools_fastq_parsing.py
crispr_ambiguous_mapping/postprocessing/__init__.py
crispr_ambiguous_mapping/postprocessing/prepare_anndata.py
crispr_ambiguous_mapping/processing/__init__.py
crispr_ambiguous_mapping/processing/crispr_count_processing.py
crispr_ambiguous_mapping/processing/crispr_editing_processing.py
crispr_ambiguous_mapping/processing/crispr_guide_counting.py
crispr_ambiguous_mapping/processing/crispr_guide_inference.py
crispr_ambiguous_mapping/processing/crispr_sequence_encoding.py
crispr_ambiguous_mapping/quality_control/__init__.py
crispr_ambiguous_mapping/quality_control/crispr_count_series_quality_control.py
crispr_ambiguous_mapping/quality_control/crispr_mapping_quality_control.py
crispr_ambiguous_mapping/utility/__init__.py
crispr_ambiguous_mapping/utility/bam2fastq.py
crispr_ambiguous_mapping/utility/crispr_editing_utility.py
crispr_ambiguous_mapping/utility/crispr_parsing_utility.py
crispr_ambiguous_mapping/utility/pickle_loading.py
crispr_ambiguous_mapping/visualization/__init__.py
crispr_ambiguous_mapping/visualization/crispr_editing_visualization.py
crispr_ambiguous_mapping-0.0.211.dist-info/METADATA
crispr_ambiguous_mapping-0.0.211.dist-info/WHEEL
crispr_ambiguous_mapping-0.0.211.dist-info/RECORD
