Metadata-Version: 2.1
Name: crispr-ambiguous-mapping
Version: 0.0.211
Summary: 
Author: Basheer Becerra
Author-email: bbecerr@outlook.com
Requires-Python: >=3.8,<3.12
Classifier: Programming Language :: Python :: 3
Classifier: Programming Language :: Python :: 3.8
Classifier: Programming Language :: Python :: 3.9
Classifier: Programming Language :: Python :: 3.10
Classifier: Programming Language :: Python :: 3.11
Requires-Dist: anndata (>=0.11.1,<0.12.0)
Requires-Dist: biopython (>=1.81,<2.0)
Requires-Dist: matplotlib (>=3.7.1,<4.0.0)
Requires-Dist: numpy (>=1.24.4,<2.0.0)
Requires-Dist: pandarallel (>=1.6.4,<2.0.0)
Requires-Dist: pandas (>=1.5.3,<2.0.0)
Requires-Dist: pysam (>=0.22.1,<0.23.0)
Requires-Dist: scipy (>=1.10.1,<2.0.0)
Requires-Dist: seaborn (>=0.13.2,<0.14.0)
Requires-Dist: typeguard (>=3.0.2,<4.0.0)
